honeybee_energy_standards/__init__.py
honeybee_energy_standards/building_mix.json
honeybee_energy_standards/hvac_registry.json
honeybee_energy_standards/constructions/opaque_construction.json
honeybee_energy_standards/constructions/opaque_material.json
honeybee_energy_standards/constructions/window_construction.json
honeybee_energy_standards/constructions/window_material.json
honeybee_energy_standards/constructionsets/1980_2004_data.json
honeybee_energy_standards/constructionsets/2004_data.json
honeybee_energy_standards/constructionsets/2007_data.json
honeybee_energy_standards/constructionsets/2010_data.json
honeybee_energy_standards/constructionsets/2013_data.json
honeybee_energy_standards/constructionsets/2016_data.json
honeybee_energy_standards/constructionsets/2019_data.json
honeybee_energy_standards/constructionsets/pre_1980_data.json
honeybee_energy_standards/programtypes/1980_2004_data.json
honeybee_energy_standards/programtypes/2004_data.json
honeybee_energy_standards/programtypes/2007_data.json
honeybee_energy_standards/programtypes/2010_data.json
honeybee_energy_standards/programtypes/2013_data.json
honeybee_energy_standards/programtypes/2016_data.json
honeybee_energy_standards/programtypes/2019_data.json
honeybee_energy_standards/programtypes/pre_1980_data.json
honeybee_energy_standards/programtypes_registry/1980_2004_registry.json
honeybee_energy_standards/programtypes_registry/2004_registry.json
honeybee_energy_standards/programtypes_registry/2007_registry.json
honeybee_energy_standards/programtypes_registry/2010_registry.json
honeybee_energy_standards/programtypes_registry/2013_registry.json
honeybee_energy_standards/programtypes_registry/2016_registry.json
honeybee_energy_standards/programtypes_registry/2019_registry.json
honeybee_energy_standards/programtypes_registry/pre_1980_registry.json
honeybee_energy_standards/schedules/schedule.json
honeybee_energy_standards-2.2.6.dist-info/LICENSE
honeybee_energy_standards-2.2.6.dist-info/METADATA
honeybee_energy_standards-2.2.6.dist-info/WHEEL
honeybee_energy_standards-2.2.6.dist-info/top_level.txt
honeybee_energy_standards-2.2.6.dist-info/RECORD
