Metadata-Version: 2.1
Name: honeybee-energy-standards
Version: 2.2.6
Summary: Honeybee-energy extension for standards, codes, and templates.
Home-page: https://github.com/ladybug-tools/honeybee-energy-standards
Author: Ladybug Tools
Author-email: info@ladybug.tools
License: AGPL-3.0
Platform: UNKNOWN
Classifier: Programming Language :: Python :: 2.7
Classifier: Programming Language :: Python :: 3.6
Classifier: Programming Language :: Python :: 3.7
Classifier: Programming Language :: Python :: Implementation :: CPython
Classifier: License :: OSI Approved :: GNU Affero General Public License v3
Classifier: Operating System :: OS Independent
License-File: LICENSE
